{
    "r-annotationdbi-spack-v0.11.0-r-annotationdbi-spack-v0.11.0": {
        "spec1": "r-annotationdbi-spack-v0.11.0",
        "spec2": "r-annotationdbi-spack-v0.11.0",
        "1_package_name_overlap": 1,
        "2_package_name_version_exact": 1,
        "3_package_weighted_versions": 1,
        "4_parameter_overlap": 1,
        "5_arch_overlap": 1
    },
    "r-annotationdbi-spack-v0.11.0-r-annotationdbi-spack-v0.11.1": {
        "spec1": "r-annotationdbi-spack-v0.11.0",
        "spec2": "r-annotationdbi-spack-v0.11.1",
        "1_package_name_overlap": 1.0,
        "2_package_name_version_exact": 0.96875,
        "3_package_weighted_versions": 0.9999254787987182,
        "4_parameter_overlap": 0.14285714285714285,
        "5_arch_overlap": 0.873015873015873
    },
    "r-annotationdbi-spack-v0.11.0-r-annotationdbi-spack-v0.11.2": {
        "spec1": "r-annotationdbi-spack-v0.11.0",
        "spec2": "r-annotationdbi-spack-v0.11.2",
        "1_package_name_overlap": 0.9682539682539683,
        "2_package_name_version_exact": 0.6986301369863014,
        "3_package_weighted_versions": 0.915755249506636,
        "4_parameter_overlap": 0.14285714285714285,
        "5_arch_overlap": 0.8412698412698413
    },
    "r-annotationdbi-spack-v0.11.0-r-annotationdbi-spack-v0.12.0": {
        "spec1": "r-annotationdbi-spack-v0.11.0",
        "spec2": "r-annotationdbi-spack-v0.12.0",
        "1_package_name_overlap": 0.9682539682539683,
        "2_package_name_version_exact": 0.2916666666666667,
        "3_package_weighted_versions": 0.7346491978164366,
        "4_parameter_overlap": 0.08888888888888888,
        "5_arch_overlap": 0.8412698412698413
    },
    "r-annotationdbi-spack-v0.11.0-r-annotationdbi-spack-v0.12.1": {
        "spec1": "r-annotationdbi-spack-v0.11.0",
        "spec2": "r-annotationdbi-spack-v0.12.1",
        "1_package_name_overlap": 0.9682539682539683,
        "2_package_name_version_exact": 0.2916666666666667,
        "3_package_weighted_versions": 0.7346491978164366,
        "4_parameter_overlap": 0.08888888888888888,
        "5_arch_overlap": 0.8412698412698413
    },
    "r-annotationdbi-spack-v0.11.0-r-annotationdbi-spack-v0.14.0": {
        "spec1": "r-annotationdbi-spack-v0.11.0",
        "spec2": "r-annotationdbi-spack-v0.14.0",
        "1_package_name_overlap": 0.5204081632653061,
        "2_package_name_version_exact": 0.034722222222222224,
        "3_package_weighted_versions": 0.1278023782521137,
        "4_parameter_overlap": 0.04907677356656948,
        "5_arch_overlap": 0.22448979591836735
    },
    "r-annotationdbi-spack-v0.11.0-r-annotationdbi-spack-v0.14.1": {
        "spec1": "r-annotationdbi-spack-v0.11.0",
        "spec2": "r-annotationdbi-spack-v0.14.1",
        "1_package_name_overlap": 0.5204081632653061,
        "2_package_name_version_exact": 0.034722222222222224,
        "3_package_weighted_versions": 0.1278023782521137,
        "4_parameter_overlap": 0.04907677356656948,
        "5_arch_overlap": 0.22448979591836735
    },
    "r-annotationdbi-spack-v0.11.0-r-annotationdbi-spack-v0.14.2": {
        "spec1": "r-annotationdbi-spack-v0.11.0",
        "spec2": "r-annotationdbi-spack-v0.14.2",
        "1_package_name_overlap": 0.5204081632653061,
        "2_package_name_version_exact": 0.034722222222222224,
        "3_package_weighted_versions": 0.1278023782521137,
        "4_parameter_overlap": 0.04907677356656948,
        "5_arch_overlap": 0.22448979591836735
    },
    "r-annotationdbi-spack-v0.11.0-r-annotationdbi-spack-v0.15.0": {
        "spec1": "r-annotationdbi-spack-v0.11.0",
        "spec2": "r-annotationdbi-spack-v0.15.0",
        "1_package_name_overlap": 0.5,
        "2_package_name_version_exact": 0.026845637583892617,
        "3_package_weighted_versions": 0.08148576530723792,
        "4_parameter_overlap": 0.042156862745098035,
        "5_arch_overlap": 0.21568627450980393
    },
    "r-annotationdbi-spack-v0.11.0-r-annotationdbi-spack-v0.15.1": {
        "spec1": "r-annotationdbi-spack-v0.11.0",
        "spec2": "r-annotationdbi-spack-v0.15.1",
        "1_package_name_overlap": 0.5,
        "2_package_name_version_exact": 0.026845637583892617,
        "3_package_weighted_versions": 0.08148576530723792,
        "4_parameter_overlap": 0.042156862745098035,
        "5_arch_overlap": 0.21568627450980393
    },
    "r-annotationdbi-spack-v0.11.0-r-annotationdbi-spack-v0.15.2": {
        "spec1": "r-annotationdbi-spack-v0.11.0",
        "spec2": "r-annotationdbi-spack-v0.15.2",
        "1_package_name_overlap": 0.5,
        "2_package_name_version_exact": 0.026845637583892617,
        "3_package_weighted_versions": 0.08148576530723792,
        "4_parameter_overlap": 0.042156862745098035,
        "5_arch_overlap": 0.21568627450980393
    },
    "r-annotationdbi-spack-v0.11.0-r-annotationdbi-spack-v0.15.3": {
        "spec1": "r-annotationdbi-spack-v0.11.0",
        "spec2": "r-annotationdbi-spack-v0.15.3",
        "1_package_name_overlap": 0.5,
        "2_package_name_version_exact": 0.026845637583892617,
        "3_package_weighted_versions": 0.08148576530723792,
        "4_parameter_overlap": 0.042156862745098035,
        "5_arch_overlap": 0.21568627450980393
    },
    "r-annotationdbi-spack-v0.11.0-r-annotationdbi-spack-v0.15.4": {
        "spec1": "r-annotationdbi-spack-v0.11.0",
        "spec2": "r-annotationdbi-spack-v0.15.4",
        "1_package_name_overlap": 0.5,
        "2_package_name_version_exact": 0.026845637583892617,
        "3_package_weighted_versions": 0.08148576530723792,
        "4_parameter_overlap": 0.042156862745098035,
        "5_arch_overlap": 0.21568627450980393
    },
    "r-annotationdbi-spack-v0.11.0-r-annotationdbi-spack-v0.16.0": {
        "spec1": "r-annotationdbi-spack-v0.11.0",
        "spec2": "r-annotationdbi-spack-v0.16.0",
        "1_package_name_overlap": 0.4857142857142857,
        "2_package_name_version_exact": 0.02631578947368421,
        "3_package_weighted_versions": 0.057515661594235525,
        "4_parameter_overlap": 0.040873015873015874,
        "5_arch_overlap": 0.20952380952380953
    },
    "r-annotationdbi-spack-v0.11.0-r-annotationdbi-spack-v0.16.1": {
        "spec1": "r-annotationdbi-spack-v0.11.0",
        "spec2": "r-annotationdbi-spack-v0.16.1",
        "1_package_name_overlap": 0.4857142857142857,
        "2_package_name_version_exact": 0.02631578947368421,
        "3_package_weighted_versions": 0.057515661594235525,
        "4_parameter_overlap": 0.040873015873015874,
        "5_arch_overlap": 0.20952380952380953
    },
    "r-annotationdbi-spack-v0.11.1-r-annotationdbi-spack-v0.11.1": {
        "spec1": "r-annotationdbi-spack-v0.11.1",
        "spec2": "r-annotationdbi-spack-v0.11.1",
        "1_package_name_overlap": 1,
        "2_package_name_version_exact": 1,
        "3_package_weighted_versions": 1,
        "4_parameter_overlap": 1,
        "5_arch_overlap": 1
    },
    "r-annotationdbi-spack-v0.11.1-r-annotationdbi-spack-v0.11.2": {
        "spec1": "r-annotationdbi-spack-v0.11.1",
        "spec2": "r-annotationdbi-spack-v0.11.2",
        "1_package_name_overlap": 0.9682539682539683,
        "2_package_name_version_exact": 0.7222222222222222,
        "3_package_weighted_versions": 0.9158297707079177,
        "4_parameter_overlap": 0.14285714285714285,
        "5_arch_overlap": 0.8412698412698413
    },
    "r-annotationdbi-spack-v0.11.1-r-annotationdbi-spack-v0.12.0": {
        "spec1": "r-annotationdbi-spack-v0.11.1",
        "spec2": "r-annotationdbi-spack-v0.12.0",
        "1_package_name_overlap": 0.9682539682539683,
        "2_package_name_version_exact": 0.2916666666666667,
        "3_package_weighted_versions": 0.7347237190177183,
        "4_parameter_overlap": 0.08888888888888888,
        "5_arch_overlap": 0.8412698412698413
    },
    "r-annotationdbi-spack-v0.11.1-r-annotationdbi-spack-v0.12.1": {
        "spec1": "r-annotationdbi-spack-v0.11.1",
        "spec2": "r-annotationdbi-spack-v0.12.1",
        "1_package_name_overlap": 0.9682539682539683,
        "2_package_name_version_exact": 0.2916666666666667,
        "3_package_weighted_versions": 0.7347237190177183,
        "4_parameter_overlap": 0.08888888888888888,
        "5_arch_overlap": 0.8412698412698413
    },
    "r-annotationdbi-spack-v0.11.1-r-annotationdbi-spack-v0.14.0": {
        "spec1": "r-annotationdbi-spack-v0.11.1",
        "spec2": "r-annotationdbi-spack-v0.14.0",
        "1_package_name_overlap": 0.5204081632653061,
        "2_package_name_version_exact": 0.034722222222222224,
        "3_package_weighted_versions": 0.12775447176557542,
        "4_parameter_overlap": 0.04907677356656948,
        "5_arch_overlap": 0.22448979591836735
    },
    "r-annotationdbi-spack-v0.11.1-r-annotationdbi-spack-v0.14.1": {
        "spec1": "r-annotationdbi-spack-v0.11.1",
        "spec2": "r-annotationdbi-spack-v0.14.1",
        "1_package_name_overlap": 0.5204081632653061,
        "2_package_name_version_exact": 0.034722222222222224,
        "3_package_weighted_versions": 0.12775447176557542,
        "4_parameter_overlap": 0.04907677356656948,
        "5_arch_overlap": 0.22448979591836735
    },
    "r-annotationdbi-spack-v0.11.1-r-annotationdbi-spack-v0.14.2": {
        "spec1": "r-annotationdbi-spack-v0.11.1",
        "spec2": "r-annotationdbi-spack-v0.14.2",
        "1_package_name_overlap": 0.5204081632653061,
        "2_package_name_version_exact": 0.034722222222222224,
        "3_package_weighted_versions": 0.12775447176557542,
        "4_parameter_overlap": 0.04907677356656948,
        "5_arch_overlap": 0.22448979591836735
    },
    "r-annotationdbi-spack-v0.11.1-r-annotationdbi-spack-v0.15.0": {
        "spec1": "r-annotationdbi-spack-v0.11.1",
        "spec2": "r-annotationdbi-spack-v0.15.0",
        "1_package_name_overlap": 0.5,
        "2_package_name_version_exact": 0.026845637583892617,
        "3_package_weighted_versions": 0.08143973750644626,
        "4_parameter_overlap": 0.042156862745098035,
        "5_arch_overlap": 0.21568627450980393
    },
    "r-annotationdbi-spack-v0.11.1-r-annotationdbi-spack-v0.15.1": {
        "spec1": "r-annotationdbi-spack-v0.11.1",
        "spec2": "r-annotationdbi-spack-v0.15.1",
        "1_package_name_overlap": 0.5,
        "2_package_name_version_exact": 0.026845637583892617,
        "3_package_weighted_versions": 0.08143973750644626,
        "4_parameter_overlap": 0.042156862745098035,
        "5_arch_overlap": 0.21568627450980393
    },
    "r-annotationdbi-spack-v0.11.1-r-annotationdbi-spack-v0.15.2": {
        "spec1": "r-annotationdbi-spack-v0.11.1",
        "spec2": "r-annotationdbi-spack-v0.15.2",
        "1_package_name_overlap": 0.5,
        "2_package_name_version_exact": 0.026845637583892617,
        "3_package_weighted_versions": 0.08143973750644626,
        "4_parameter_overlap": 0.042156862745098035,
        "5_arch_overlap": 0.21568627450980393
    },
    "r-annotationdbi-spack-v0.11.1-r-annotationdbi-spack-v0.15.3": {
        "spec1": "r-annotationdbi-spack-v0.11.1",
        "spec2": "r-annotationdbi-spack-v0.15.3",
        "1_package_name_overlap": 0.5,
        "2_package_name_version_exact": 0.026845637583892617,
        "3_package_weighted_versions": 0.08143973750644626,
        "4_parameter_overlap": 0.042156862745098035,
        "5_arch_overlap": 0.21568627450980393
    },
    "r-annotationdbi-spack-v0.11.1-r-annotationdbi-spack-v0.15.4": {
        "spec1": "r-annotationdbi-spack-v0.11.1",
        "spec2": "r-annotationdbi-spack-v0.15.4",
        "1_package_name_overlap": 0.5,
        "2_package_name_version_exact": 0.026845637583892617,
        "3_package_weighted_versions": 0.08143973750644626,
        "4_parameter_overlap": 0.042156862745098035,
        "5_arch_overlap": 0.21568627450980393
    },
    "r-annotationdbi-spack-v0.11.1-r-annotationdbi-spack-v0.16.0": {
        "spec1": "r-annotationdbi-spack-v0.11.1",
        "spec2": "r-annotationdbi-spack-v0.16.0",
        "1_package_name_overlap": 0.4857142857142857,
        "2_package_name_version_exact": 0.02631578947368421,
        "3_package_weighted_versions": 0.05747094887346647,
        "4_parameter_overlap": 0.040873015873015874,
        "5_arch_overlap": 0.20952380952380953
    },
    "r-annotationdbi-spack-v0.11.1-r-annotationdbi-spack-v0.16.1": {
        "spec1": "r-annotationdbi-spack-v0.11.1",
        "spec2": "r-annotationdbi-spack-v0.16.1",
        "1_package_name_overlap": 0.4857142857142857,
        "2_package_name_version_exact": 0.02631578947368421,
        "3_package_weighted_versions": 0.05747094887346647,
        "4_parameter_overlap": 0.040873015873015874,
        "5_arch_overlap": 0.20952380952380953
    },
    "r-annotationdbi-spack-v0.11.2-r-annotationdbi-spack-v0.11.2": {
        "spec1": "r-annotationdbi-spack-v0.11.2",
        "spec2": "r-annotationdbi-spack-v0.11.2",
        "1_package_name_overlap": 1,
        "2_package_name_version_exact": 1,
        "3_package_weighted_versions": 1,
        "4_parameter_overlap": 1,
        "5_arch_overlap": 1
    },
    "r-annotationdbi-spack-v0.11.2-r-annotationdbi-spack-v0.12.0": {
        "spec1": "r-annotationdbi-spack-v0.11.2",
        "spec2": "r-annotationdbi-spack-v0.12.0",
        "1_package_name_overlap": 1.0,
        "2_package_name_version_exact": 0.35555555555555557,
        "3_package_weighted_versions": 0.7965626023527446,
        "4_parameter_overlap": 0.09180327868852459,
        "5_arch_overlap": 0.8688524590163934
    },
    "r-annotationdbi-spack-v0.11.2-r-annotationdbi-spack-v0.12.1": {
        "spec1": "r-annotationdbi-spack-v0.11.2",
        "spec2": "r-annotationdbi-spack-v0.12.1",
        "1_package_name_overlap": 1.0,
        "2_package_name_version_exact": 0.35555555555555557,
        "3_package_weighted_versions": 0.7965626023527446,
        "4_parameter_overlap": 0.09180327868852459,
        "5_arch_overlap": 0.8688524590163934
    },
    "r-annotationdbi-spack-v0.11.2-r-annotationdbi-spack-v0.14.0": {
        "spec1": "r-annotationdbi-spack-v0.11.2",
        "spec2": "r-annotationdbi-spack-v0.14.0",
        "1_package_name_overlap": 0.53125,
        "2_package_name_version_exact": 0.0425531914893617,
        "3_package_weighted_versions": 0.14686727524071286,
        "4_parameter_overlap": 0.050099206349206345,
        "5_arch_overlap": 0.22916666666666666
    },
    "r-annotationdbi-spack-v0.11.2-r-annotationdbi-spack-v0.14.1": {
        "spec1": "r-annotationdbi-spack-v0.11.2",
        "spec2": "r-annotationdbi-spack-v0.14.1",
        "1_package_name_overlap": 0.53125,
        "2_package_name_version_exact": 0.0425531914893617,
        "3_package_weighted_versions": 0.14686727524071286,
        "4_parameter_overlap": 0.050099206349206345,
        "5_arch_overlap": 0.22916666666666666
    },
    "r-annotationdbi-spack-v0.11.2-r-annotationdbi-spack-v0.14.2": {
        "spec1": "r-annotationdbi-spack-v0.11.2",
        "spec2": "r-annotationdbi-spack-v0.14.2",
        "1_package_name_overlap": 0.53125,
        "2_package_name_version_exact": 0.0425531914893617,
        "3_package_weighted_versions": 0.14686727524071286,
        "4_parameter_overlap": 0.050099206349206345,
        "5_arch_overlap": 0.22916666666666666
    },
    "r-annotationdbi-spack-v0.11.2-r-annotationdbi-spack-v0.15.0": {
        "spec1": "r-annotationdbi-spack-v0.11.2",
        "spec2": "r-annotationdbi-spack-v0.15.0",
        "1_package_name_overlap": 0.51,
        "2_package_name_version_exact": 0.03424657534246575,
        "3_package_weighted_versions": 0.09886173415739563,
        "4_parameter_overlap": 0.043,
        "5_arch_overlap": 0.22
    },
    "r-annotationdbi-spack-v0.11.2-r-annotationdbi-spack-v0.15.1": {
        "spec1": "r-annotationdbi-spack-v0.11.2",
        "spec2": "r-annotationdbi-spack-v0.15.1",
        "1_package_name_overlap": 0.51,
        "2_package_name_version_exact": 0.03424657534246575,
        "3_package_weighted_versions": 0.09886173415739563,
        "4_parameter_overlap": 0.043,
        "5_arch_overlap": 0.22
    },
    "r-annotationdbi-spack-v0.11.2-r-annotationdbi-spack-v0.15.2": {
        "spec1": "r-annotationdbi-spack-v0.11.2",
        "spec2": "r-annotationdbi-spack-v0.15.2",
        "1_package_name_overlap": 0.51,
        "2_package_name_version_exact": 0.03424657534246575,
        "3_package_weighted_versions": 0.09886173415739563,
        "4_parameter_overlap": 0.043,
        "5_arch_overlap": 0.22
    },
    "r-annotationdbi-spack-v0.11.2-r-annotationdbi-spack-v0.15.3": {
        "spec1": "r-annotationdbi-spack-v0.11.2",
        "spec2": "r-annotationdbi-spack-v0.15.3",
        "1_package_name_overlap": 0.51,
        "2_package_name_version_exact": 0.03424657534246575,
        "3_package_weighted_versions": 0.09886173415739563,
        "4_parameter_overlap": 0.043,
        "5_arch_overlap": 0.22
    },
    "r-annotationdbi-spack-v0.11.2-r-annotationdbi-spack-v0.15.4": {
        "spec1": "r-annotationdbi-spack-v0.11.2",
        "spec2": "r-annotationdbi-spack-v0.15.4",
        "1_package_name_overlap": 0.51,
        "2_package_name_version_exact": 0.03424657534246575,
        "3_package_weighted_versions": 0.09886173415739563,
        "4_parameter_overlap": 0.043,
        "5_arch_overlap": 0.22
    },
    "r-annotationdbi-spack-v0.11.2-r-annotationdbi-spack-v0.16.0": {
        "spec1": "r-annotationdbi-spack-v0.11.2",
        "spec2": "r-annotationdbi-spack-v0.16.0",
        "1_package_name_overlap": 0.49514563106796117,
        "2_package_name_version_exact": 0.03355704697986577,
        "3_package_weighted_versions": 0.07392009535724293,
        "4_parameter_overlap": 0.04166666666666667,
        "5_arch_overlap": 0.21359223300970873
    },
    "r-annotationdbi-spack-v0.11.2-r-annotationdbi-spack-v0.16.1": {
        "spec1": "r-annotationdbi-spack-v0.11.2",
        "spec2": "r-annotationdbi-spack-v0.16.1",
        "1_package_name_overlap": 0.49514563106796117,
        "2_package_name_version_exact": 0.03355704697986577,
        "3_package_weighted_versions": 0.07392009535724293,
        "4_parameter_overlap": 0.04166666666666667,
        "5_arch_overlap": 0.21359223300970873
    },
    "r-annotationdbi-spack-v0.12.0-r-annotationdbi-spack-v0.12.0": {
        "spec1": "r-annotationdbi-spack-v0.12.0",
        "spec2": "r-annotationdbi-spack-v0.12.0",
        "1_package_name_overlap": 1,
        "2_package_name_version_exact": 1,
        "3_package_weighted_versions": 1,
        "4_parameter_overlap": 1,
        "5_arch_overlap": 1
    },
    "r-annotationdbi-spack-v0.12.0-r-annotationdbi-spack-v0.12.1": {
        "spec1": "r-annotationdbi-spack-v0.12.0",
        "spec2": "r-annotationdbi-spack-v0.12.1",
        "1_package_name_overlap": 1.0,
        "2_package_name_version_exact": 1.0,
        "3_package_weighted_versions": 1.0,
        "4_parameter_overlap": 0.11475409836065574,
        "5_arch_overlap": 0.8688524590163934
    },
    "r-annotationdbi-spack-v0.12.0-r-annotationdbi-spack-v0.14.0": {
        "spec1": "r-annotationdbi-spack-v0.12.0",
        "spec2": "r-annotationdbi-spack-v0.14.0",
        "1_package_name_overlap": 0.53125,
        "2_package_name_version_exact": 0.08088235294117647,
        "3_package_weighted_versions": 0.2319576886942268,
        "4_parameter_overlap": 0.050719246031746025,
        "5_arch_overlap": 0.22916666666666666
    },
    "r-annotationdbi-spack-v0.12.0-r-annotationdbi-spack-v0.14.1": {
        "spec1": "r-annotationdbi-spack-v0.12.0",
        "spec2": "r-annotationdbi-spack-v0.14.1",
        "1_package_name_overlap": 0.53125,
        "2_package_name_version_exact": 0.08088235294117647,
        "3_package_weighted_versions": 0.2319576886942268,
        "4_parameter_overlap": 0.050719246031746025,
        "5_arch_overlap": 0.22916666666666666
    },
    "r-annotationdbi-spack-v0.12.0-r-annotationdbi-spack-v0.14.2": {
        "spec1": "r-annotationdbi-spack-v0.12.0",
        "spec2": "r-annotationdbi-spack-v0.14.2",
        "1_package_name_overlap": 0.53125,
        "2_package_name_version_exact": 0.08088235294117647,
        "3_package_weighted_versions": 0.2319576886942268,
        "4_parameter_overlap": 0.050719246031746025,
        "5_arch_overlap": 0.22916666666666666
    },
    "r-annotationdbi-spack-v0.12.0-r-annotationdbi-spack-v0.15.0": {
        "spec1": "r-annotationdbi-spack-v0.12.0",
        "spec2": "r-annotationdbi-spack-v0.15.0",
        "1_package_name_overlap": 0.51,
        "2_package_name_version_exact": 0.055944055944055944,
        "3_package_weighted_versions": 0.17054853107276888,
        "4_parameter_overlap": 0.04516666666666667,
        "5_arch_overlap": 0.22
    },
    "r-annotationdbi-spack-v0.12.0-r-annotationdbi-spack-v0.15.1": {
        "spec1": "r-annotationdbi-spack-v0.12.0",
        "spec2": "r-annotationdbi-spack-v0.15.1",
        "1_package_name_overlap": 0.51,
        "2_package_name_version_exact": 0.055944055944055944,
        "3_package_weighted_versions": 0.17054853107276888,
        "4_parameter_overlap": 0.04516666666666667,
        "5_arch_overlap": 0.22
    },
    "r-annotationdbi-spack-v0.12.0-r-annotationdbi-spack-v0.15.2": {
        "spec1": "r-annotationdbi-spack-v0.12.0",
        "spec2": "r-annotationdbi-spack-v0.15.2",
        "1_package_name_overlap": 0.51,
        "2_package_name_version_exact": 0.055944055944055944,
        "3_package_weighted_versions": 0.17054853107276888,
        "4_parameter_overlap": 0.04516666666666667,
        "5_arch_overlap": 0.22
    },
    "r-annotationdbi-spack-v0.12.0-r-annotationdbi-spack-v0.15.3": {
        "spec1": "r-annotationdbi-spack-v0.12.0",
        "spec2": "r-annotationdbi-spack-v0.15.3",
        "1_package_name_overlap": 0.51,
        "2_package_name_version_exact": 0.055944055944055944,
        "3_package_weighted_versions": 0.17054853107276888,
        "4_parameter_overlap": 0.04516666666666667,
        "5_arch_overlap": 0.22
    },
    "r-annotationdbi-spack-v0.12.0-r-annotationdbi-spack-v0.15.4": {
        "spec1": "r-annotationdbi-spack-v0.12.0",
        "spec2": "r-annotationdbi-spack-v0.15.4",
        "1_package_name_overlap": 0.51,
        "2_package_name_version_exact": 0.055944055944055944,
        "3_package_weighted_versions": 0.17054853107276888,
        "4_parameter_overlap": 0.04516666666666667,
        "5_arch_overlap": 0.22
    },
    "r-annotationdbi-spack-v0.12.0-r-annotationdbi-spack-v0.16.0": {
        "spec1": "r-annotationdbi-spack-v0.12.0",
        "spec2": "r-annotationdbi-spack-v0.16.0",
        "1_package_name_overlap": 0.49514563106796117,
        "2_package_name_version_exact": 0.047619047619047616,
        "3_package_weighted_versions": 0.14012857440899998,
        "4_parameter_overlap": 0.043689320388349516,
        "5_arch_overlap": 0.21359223300970873
    },
    "r-annotationdbi-spack-v0.12.0-r-annotationdbi-spack-v0.16.1": {
        "spec1": "r-annotationdbi-spack-v0.12.0",
        "spec2": "r-annotationdbi-spack-v0.16.1",
        "1_package_name_overlap": 0.49514563106796117,
        "2_package_name_version_exact": 0.047619047619047616,
        "3_package_weighted_versions": 0.14012857440899998,
        "4_parameter_overlap": 0.043689320388349516,
        "5_arch_overlap": 0.21359223300970873
    },
    "r-annotationdbi-spack-v0.12.1-r-annotationdbi-spack-v0.12.1": {
        "spec1": "r-annotationdbi-spack-v0.12.1",
        "spec2": "r-annotationdbi-spack-v0.12.1",
        "1_package_name_overlap": 1,
        "2_package_name_version_exact": 1,
        "3_package_weighted_versions": 1,
        "4_parameter_overlap": 1,
        "5_arch_overlap": 1
    },
    "r-annotationdbi-spack-v0.12.1-r-annotationdbi-spack-v0.14.0": {
        "spec1": "r-annotationdbi-spack-v0.12.1",
        "spec2": "r-annotationdbi-spack-v0.14.0",
        "1_package_name_overlap": 0.53125,
        "2_package_name_version_exact": 0.08088235294117647,
        "3_package_weighted_versions": 0.2319576886942268,
        "4_parameter_overlap": 0.050719246031746025,
        "5_arch_overlap": 0.22916666666666666
    },
    "r-annotationdbi-spack-v0.12.1-r-annotationdbi-spack-v0.14.1": {
        "spec1": "r-annotationdbi-spack-v0.12.1",
        "spec2": "r-annotationdbi-spack-v0.14.1",
        "1_package_name_overlap": 0.53125,
        "2_package_name_version_exact": 0.08088235294117647,
        "3_package_weighted_versions": 0.2319576886942268,
        "4_parameter_overlap": 0.050719246031746025,
        "5_arch_overlap": 0.22916666666666666
    },
    "r-annotationdbi-spack-v0.12.1-r-annotationdbi-spack-v0.14.2": {
        "spec1": "r-annotationdbi-spack-v0.12.1",
        "spec2": "r-annotationdbi-spack-v0.14.2",
        "1_package_name_overlap": 0.53125,
        "2_package_name_version_exact": 0.08088235294117647,
        "3_package_weighted_versions": 0.2319576886942268,
        "4_parameter_overlap": 0.050719246031746025,
        "5_arch_overlap": 0.22916666666666666
    },
    "r-annotationdbi-spack-v0.12.1-r-annotationdbi-spack-v0.15.0": {
        "spec1": "r-annotationdbi-spack-v0.12.1",
        "spec2": "r-annotationdbi-spack-v0.15.0",
        "1_package_name_overlap": 0.51,
        "2_package_name_version_exact": 0.055944055944055944,
        "3_package_weighted_versions": 0.17054853107276888,
        "4_parameter_overlap": 0.04516666666666667,
        "5_arch_overlap": 0.22
    },
    "r-annotationdbi-spack-v0.12.1-r-annotationdbi-spack-v0.15.1": {
        "spec1": "r-annotationdbi-spack-v0.12.1",
        "spec2": "r-annotationdbi-spack-v0.15.1",
        "1_package_name_overlap": 0.51,
        "2_package_name_version_exact": 0.055944055944055944,
        "3_package_weighted_versions": 0.17054853107276888,
        "4_parameter_overlap": 0.04516666666666667,
        "5_arch_overlap": 0.22
    },
    "r-annotationdbi-spack-v0.12.1-r-annotationdbi-spack-v0.15.2": {
        "spec1": "r-annotationdbi-spack-v0.12.1",
        "spec2": "r-annotationdbi-spack-v0.15.2",
        "1_package_name_overlap": 0.51,
        "2_package_name_version_exact": 0.055944055944055944,
        "3_package_weighted_versions": 0.17054853107276888,
        "4_parameter_overlap": 0.04516666666666667,
        "5_arch_overlap": 0.22
    },
    "r-annotationdbi-spack-v0.12.1-r-annotationdbi-spack-v0.15.3": {
        "spec1": "r-annotationdbi-spack-v0.12.1",
        "spec2": "r-annotationdbi-spack-v0.15.3",
        "1_package_name_overlap": 0.51,
        "2_package_name_version_exact": 0.055944055944055944,
        "3_package_weighted_versions": 0.17054853107276888,
        "4_parameter_overlap": 0.04516666666666667,
        "5_arch_overlap": 0.22
    },
    "r-annotationdbi-spack-v0.12.1-r-annotationdbi-spack-v0.15.4": {
        "spec1": "r-annotationdbi-spack-v0.12.1",
        "spec2": "r-annotationdbi-spack-v0.15.4",
        "1_package_name_overlap": 0.51,
        "2_package_name_version_exact": 0.055944055944055944,
        "3_package_weighted_versions": 0.17054853107276888,
        "4_parameter_overlap": 0.04516666666666667,
        "5_arch_overlap": 0.22
    },
    "r-annotationdbi-spack-v0.12.1-r-annotationdbi-spack-v0.16.0": {
        "spec1": "r-annotationdbi-spack-v0.12.1",
        "spec2": "r-annotationdbi-spack-v0.16.0",
        "1_package_name_overlap": 0.49514563106796117,
        "2_package_name_version_exact": 0.047619047619047616,
        "3_package_weighted_versions": 0.14012857440899998,
        "4_parameter_overlap": 0.043689320388349516,
        "5_arch_overlap": 0.21359223300970873
    },
    "r-annotationdbi-spack-v0.12.1-r-annotationdbi-spack-v0.16.1": {
        "spec1": "r-annotationdbi-spack-v0.12.1",
        "spec2": "r-annotationdbi-spack-v0.16.1",
        "1_package_name_overlap": 0.49514563106796117,
        "2_package_name_version_exact": 0.047619047619047616,
        "3_package_weighted_versions": 0.14012857440899998,
        "4_parameter_overlap": 0.043689320388349516,
        "5_arch_overlap": 0.21359223300970873
    },
    "r-annotationdbi-spack-v0.14.0-r-annotationdbi-spack-v0.14.0": {
        "spec1": "r-annotationdbi-spack-v0.14.0",
        "spec2": "r-annotationdbi-spack-v0.14.0",
        "1_package_name_overlap": 1,
        "2_package_name_version_exact": 1,
        "3_package_weighted_versions": 1,
        "4_parameter_overlap": 1,
        "5_arch_overlap": 1
    },
    "r-annotationdbi-spack-v0.14.0-r-annotationdbi-spack-v0.14.1": {
        "spec1": "r-annotationdbi-spack-v0.14.0",
        "spec2": "r-annotationdbi-spack-v0.14.1",
        "1_package_name_overlap": 1.0,
        "2_package_name_version_exact": 1.0,
        "3_package_weighted_versions": 1.0,
        "4_parameter_overlap": 0.20930232558139536,
        "5_arch_overlap": 0.9069767441860465
    },
    "r-annotationdbi-spack-v0.14.0-r-annotationdbi-spack-v0.14.2": {
        "spec1": "r-annotationdbi-spack-v0.14.0",
        "spec2": "r-annotationdbi-spack-v0.14.2",
        "1_package_name_overlap": 1.0,
        "2_package_name_version_exact": 1.0,
        "3_package_weighted_versions": 1.0,
        "4_parameter_overlap": 0.20930232558139536,
        "5_arch_overlap": 0.9069767441860465
    },
    "r-annotationdbi-spack-v0.14.0-r-annotationdbi-spack-v0.15.0": {
        "spec1": "r-annotationdbi-spack-v0.14.0",
        "spec2": "r-annotationdbi-spack-v0.15.0",
        "1_package_name_overlap": 0.9555555555555556,
        "2_package_name_version_exact": 0.5855855855855856,
        "3_package_weighted_versions": 0.8237434999181233,
        "4_parameter_overlap": 0.1862433862433862,
        "5_arch_overlap": 0.8666666666666667
    },
    "r-annotationdbi-spack-v0.14.0-r-annotationdbi-spack-v0.15.1": {
        "spec1": "r-annotationdbi-spack-v0.14.0",
        "spec2": "r-annotationdbi-spack-v0.15.1",
        "1_package_name_overlap": 0.9555555555555556,
        "2_package_name_version_exact": 0.5855855855855856,
        "3_package_weighted_versions": 0.8237434999181233,
        "4_parameter_overlap": 0.1862433862433862,
        "5_arch_overlap": 0.8666666666666667
    },
    "r-annotationdbi-spack-v0.14.0-r-annotationdbi-spack-v0.15.2": {
        "spec1": "r-annotationdbi-spack-v0.14.0",
        "spec2": "r-annotationdbi-spack-v0.15.2",
        "1_package_name_overlap": 0.9555555555555556,
        "2_package_name_version_exact": 0.5855855855855856,
        "3_package_weighted_versions": 0.8237434999181233,
        "4_parameter_overlap": 0.1862433862433862,
        "5_arch_overlap": 0.8666666666666667
    },
    "r-annotationdbi-spack-v0.14.0-r-annotationdbi-spack-v0.15.3": {
        "spec1": "r-annotationdbi-spack-v0.14.0",
        "spec2": "r-annotationdbi-spack-v0.15.3",
        "1_package_name_overlap": 0.9555555555555556,
        "2_package_name_version_exact": 0.5855855855855856,
        "3_package_weighted_versions": 0.8237434999181233,
        "4_parameter_overlap": 0.1862433862433862,
        "5_arch_overlap": 0.8666666666666667
    },
    "r-annotationdbi-spack-v0.14.0-r-annotationdbi-spack-v0.15.4": {
        "spec1": "r-annotationdbi-spack-v0.14.0",
        "spec2": "r-annotationdbi-spack-v0.15.4",
        "1_package_name_overlap": 0.9555555555555556,
        "2_package_name_version_exact": 0.5855855855855856,
        "3_package_weighted_versions": 0.8237434999181233,
        "4_parameter_overlap": 0.1862433862433862,
        "5_arch_overlap": 0.8666666666666667
    },
    "r-annotationdbi-spack-v0.14.0-r-annotationdbi-spack-v0.16.0": {
        "spec1": "r-annotationdbi-spack-v0.14.0",
        "spec2": "r-annotationdbi-spack-v0.16.0",
        "1_package_name_overlap": 0.9247311827956989,
        "2_package_name_version_exact": 0.432,
        "3_package_weighted_versions": 0.7111562072226177,
        "4_parameter_overlap": 0.1661290322580645,
        "5_arch_overlap": 0.8387096774193549
    },
    "r-annotationdbi-spack-v0.14.0-r-annotationdbi-spack-v0.16.1": {
        "spec1": "r-annotationdbi-spack-v0.14.0",
        "spec2": "r-annotationdbi-spack-v0.16.1",
        "1_package_name_overlap": 0.9247311827956989,
        "2_package_name_version_exact": 0.432,
        "3_package_weighted_versions": 0.7111562072226177,
        "4_parameter_overlap": 0.1661290322580645,
        "5_arch_overlap": 0.8387096774193549
    },
    "r-annotationdbi-spack-v0.14.1-r-annotationdbi-spack-v0.14.1": {
        "spec1": "r-annotationdbi-spack-v0.14.1",
        "spec2": "r-annotationdbi-spack-v0.14.1",
        "1_package_name_overlap": 1,
        "2_package_name_version_exact": 1,
        "3_package_weighted_versions": 1,
        "4_parameter_overlap": 1,
        "5_arch_overlap": 1
    },
    "r-annotationdbi-spack-v0.14.1-r-annotationdbi-spack-v0.14.2": {
        "spec1": "r-annotationdbi-spack-v0.14.1",
        "spec2": "r-annotationdbi-spack-v0.14.2",
        "1_package_name_overlap": 1.0,
        "2_package_name_version_exact": 1.0,
        "3_package_weighted_versions": 1.0,
        "4_parameter_overlap": 0.20930232558139536,
        "5_arch_overlap": 0.9069767441860465
    },
    "r-annotationdbi-spack-v0.14.1-r-annotationdbi-spack-v0.15.0": {
        "spec1": "r-annotationdbi-spack-v0.14.1",
        "spec2": "r-annotationdbi-spack-v0.15.0",
        "1_package_name_overlap": 0.9555555555555556,
        "2_package_name_version_exact": 0.5855855855855856,
        "3_package_weighted_versions": 0.8237434999181233,
        "4_parameter_overlap": 0.1862433862433862,
        "5_arch_overlap": 0.8666666666666667
    },
    "r-annotationdbi-spack-v0.14.1-r-annotationdbi-spack-v0.15.1": {
        "spec1": "r-annotationdbi-spack-v0.14.1",
        "spec2": "r-annotationdbi-spack-v0.15.1",
        "1_package_name_overlap": 0.9555555555555556,
        "2_package_name_version_exact": 0.5855855855855856,
        "3_package_weighted_versions": 0.8237434999181233,
        "4_parameter_overlap": 0.1862433862433862,
        "5_arch_overlap": 0.8666666666666667
    },
    "r-annotationdbi-spack-v0.14.1-r-annotationdbi-spack-v0.15.2": {
        "spec1": "r-annotationdbi-spack-v0.14.1",
        "spec2": "r-annotationdbi-spack-v0.15.2",
        "1_package_name_overlap": 0.9555555555555556,
        "2_package_name_version_exact": 0.5855855855855856,
        "3_package_weighted_versions": 0.8237434999181233,
        "4_parameter_overlap": 0.1862433862433862,
        "5_arch_overlap": 0.8666666666666667
    },
    "r-annotationdbi-spack-v0.14.1-r-annotationdbi-spack-v0.15.3": {
        "spec1": "r-annotationdbi-spack-v0.14.1",
        "spec2": "r-annotationdbi-spack-v0.15.3",
        "1_package_name_overlap": 0.9555555555555556,
        "2_package_name_version_exact": 0.5855855855855856,
        "3_package_weighted_versions": 0.8237434999181233,
        "4_parameter_overlap": 0.1862433862433862,
        "5_arch_overlap": 0.8666666666666667
    },
    "r-annotationdbi-spack-v0.14.1-r-annotationdbi-spack-v0.15.4": {
        "spec1": "r-annotationdbi-spack-v0.14.1",
        "spec2": "r-annotationdbi-spack-v0.15.4",
        "1_package_name_overlap": 0.9555555555555556,
        "2_package_name_version_exact": 0.5855855855855856,
        "3_package_weighted_versions": 0.8237434999181233,
        "4_parameter_overlap": 0.1862433862433862,
        "5_arch_overlap": 0.8666666666666667
    },
    "r-annotationdbi-spack-v0.14.1-r-annotationdbi-spack-v0.16.0": {
        "spec1": "r-annotationdbi-spack-v0.14.1",
        "spec2": "r-annotationdbi-spack-v0.16.0",
        "1_package_name_overlap": 0.9247311827956989,
        "2_package_name_version_exact": 0.432,
        "3_package_weighted_versions": 0.7111562072226177,
        "4_parameter_overlap": 0.1661290322580645,
        "5_arch_overlap": 0.8387096774193549
    },
    "r-annotationdbi-spack-v0.14.1-r-annotationdbi-spack-v0.16.1": {
        "spec1": "r-annotationdbi-spack-v0.14.1",
        "spec2": "r-annotationdbi-spack-v0.16.1",
        "1_package_name_overlap": 0.9247311827956989,
        "2_package_name_version_exact": 0.432,
        "3_package_weighted_versions": 0.7111562072226177,
        "4_parameter_overlap": 0.1661290322580645,
        "5_arch_overlap": 0.8387096774193549
    },
    "r-annotationdbi-spack-v0.14.2-r-annotationdbi-spack-v0.14.2": {
        "spec1": "r-annotationdbi-spack-v0.14.2",
        "spec2": "r-annotationdbi-spack-v0.14.2",
        "1_package_name_overlap": 1,
        "2_package_name_version_exact": 1,
        "3_package_weighted_versions": 1,
        "4_parameter_overlap": 1,
        "5_arch_overlap": 1
    },
    "r-annotationdbi-spack-v0.14.2-r-annotationdbi-spack-v0.15.0": {
        "spec1": "r-annotationdbi-spack-v0.14.2",
        "spec2": "r-annotationdbi-spack-v0.15.0",
        "1_package_name_overlap": 0.9555555555555556,
        "2_package_name_version_exact": 0.5855855855855856,
        "3_package_weighted_versions": 0.8237434999181233,
        "4_parameter_overlap": 0.1862433862433862,
        "5_arch_overlap": 0.8666666666666667
    },
    "r-annotationdbi-spack-v0.14.2-r-annotationdbi-spack-v0.15.1": {
        "spec1": "r-annotationdbi-spack-v0.14.2",
        "spec2": "r-annotationdbi-spack-v0.15.1",
        "1_package_name_overlap": 0.9555555555555556,
        "2_package_name_version_exact": 0.5855855855855856,
        "3_package_weighted_versions": 0.8237434999181233,
        "4_parameter_overlap": 0.1862433862433862,
        "5_arch_overlap": 0.8666666666666667
    },
    "r-annotationdbi-spack-v0.14.2-r-annotationdbi-spack-v0.15.2": {
        "spec1": "r-annotationdbi-spack-v0.14.2",
        "spec2": "r-annotationdbi-spack-v0.15.2",
        "1_package_name_overlap": 0.9555555555555556,
        "2_package_name_version_exact": 0.5855855855855856,
        "3_package_weighted_versions": 0.8237434999181233,
        "4_parameter_overlap": 0.1862433862433862,
        "5_arch_overlap": 0.8666666666666667
    },
    "r-annotationdbi-spack-v0.14.2-r-annotationdbi-spack-v0.15.3": {
        "spec1": "r-annotationdbi-spack-v0.14.2",
        "spec2": "r-annotationdbi-spack-v0.15.3",
        "1_package_name_overlap": 0.9555555555555556,
        "2_package_name_version_exact": 0.5855855855855856,
        "3_package_weighted_versions": 0.8237434999181233,
        "4_parameter_overlap": 0.1862433862433862,
        "5_arch_overlap": 0.8666666666666667
    },
    "r-annotationdbi-spack-v0.14.2-r-annotationdbi-spack-v0.15.4": {
        "spec1": "r-annotationdbi-spack-v0.14.2",
        "spec2": "r-annotationdbi-spack-v0.15.4",
        "1_package_name_overlap": 0.9555555555555556,
        "2_package_name_version_exact": 0.5855855855855856,
        "3_package_weighted_versions": 0.8237434999181233,
        "4_parameter_overlap": 0.1862433862433862,
        "5_arch_overlap": 0.8666666666666667
    },
    "r-annotationdbi-spack-v0.14.2-r-annotationdbi-spack-v0.16.0": {
        "spec1": "r-annotationdbi-spack-v0.14.2",
        "spec2": "r-annotationdbi-spack-v0.16.0",
        "1_package_name_overlap": 0.9247311827956989,
        "2_package_name_version_exact": 0.432,
        "3_package_weighted_versions": 0.7111562072226177,
        "4_parameter_overlap": 0.1661290322580645,
        "5_arch_overlap": 0.8387096774193549
    },
    "r-annotationdbi-spack-v0.14.2-r-annotationdbi-spack-v0.16.1": {
        "spec1": "r-annotationdbi-spack-v0.14.2",
        "spec2": "r-annotationdbi-spack-v0.16.1",
        "1_package_name_overlap": 0.9247311827956989,
        "2_package_name_version_exact": 0.432,
        "3_package_weighted_versions": 0.7111562072226177,
        "4_parameter_overlap": 0.1661290322580645,
        "5_arch_overlap": 0.8387096774193549
    },
    "r-annotationdbi-spack-v0.15.0-r-annotationdbi-spack-v0.15.0": {
        "spec1": "r-annotationdbi-spack-v0.15.0",
        "spec2": "r-annotationdbi-spack-v0.15.0",
        "1_package_name_overlap": 1,
        "2_package_name_version_exact": 1,
        "3_package_weighted_versions": 1,
        "4_parameter_overlap": 1,
        "5_arch_overlap": 1
    },
    "r-annotationdbi-spack-v0.15.0-r-annotationdbi-spack-v0.15.1": {
        "spec1": "r-annotationdbi-spack-v0.15.0",
        "spec2": "r-annotationdbi-spack-v0.15.1",
        "1_package_name_overlap": 1.0,
        "2_package_name_version_exact": 1.0,
        "3_package_weighted_versions": 1.0,
        "4_parameter_overlap": 0.24444444444444444,
        "5_arch_overlap": 0.9111111111111111
    },
    "r-annotationdbi-spack-v0.15.0-r-annotationdbi-spack-v0.15.2": {
        "spec1": "r-annotationdbi-spack-v0.15.0",
        "spec2": "r-annotationdbi-spack-v0.15.2",
        "1_package_name_overlap": 1.0,
        "2_package_name_version_exact": 1.0,
        "3_package_weighted_versions": 1.0,
        "4_parameter_overlap": 0.24444444444444444,
        "5_arch_overlap": 0.9111111111111111
    },
    "r-annotationdbi-spack-v0.15.0-r-annotationdbi-spack-v0.15.3": {
        "spec1": "r-annotationdbi-spack-v0.15.0",
        "spec2": "r-annotationdbi-spack-v0.15.3",
        "1_package_name_overlap": 1.0,
        "2_package_name_version_exact": 1.0,
        "3_package_weighted_versions": 1.0,
        "4_parameter_overlap": 0.24444444444444444,
        "5_arch_overlap": 0.9111111111111111
    },
    "r-annotationdbi-spack-v0.15.0-r-annotationdbi-spack-v0.15.4": {
        "spec1": "r-annotationdbi-spack-v0.15.0",
        "spec2": "r-annotationdbi-spack-v0.15.4",
        "1_package_name_overlap": 1.0,
        "2_package_name_version_exact": 1.0,
        "3_package_weighted_versions": 1.0,
        "4_parameter_overlap": 0.24444444444444444,
        "5_arch_overlap": 0.9111111111111111
    },
    "r-annotationdbi-spack-v0.15.0-r-annotationdbi-spack-v0.16.0": {
        "spec1": "r-annotationdbi-spack-v0.15.0",
        "spec2": "r-annotationdbi-spack-v0.16.0",
        "1_package_name_overlap": 0.967741935483871,
        "2_package_name_version_exact": 0.5775862068965517,
        "3_package_weighted_versions": 0.8279635728932512,
        "4_parameter_overlap": 0.20448028673835125,
        "5_arch_overlap": 0.8817204301075269
    },
    "r-annotationdbi-spack-v0.15.0-r-annotationdbi-spack-v0.16.1": {
        "spec1": "r-annotationdbi-spack-v0.15.0",
        "spec2": "r-annotationdbi-spack-v0.16.1",
        "1_package_name_overlap": 0.967741935483871,
        "2_package_name_version_exact": 0.5775862068965517,
        "3_package_weighted_versions": 0.8279635728932512,
        "4_parameter_overlap": 0.20448028673835125,
        "5_arch_overlap": 0.8817204301075269
    },
    "r-annotationdbi-spack-v0.15.1-r-annotationdbi-spack-v0.15.1": {
        "spec1": "r-annotationdbi-spack-v0.15.1",
        "spec2": "r-annotationdbi-spack-v0.15.1",
        "1_package_name_overlap": 1,
        "2_package_name_version_exact": 1,
        "3_package_weighted_versions": 1,
        "4_parameter_overlap": 1,
        "5_arch_overlap": 1
    },
    "r-annotationdbi-spack-v0.15.1-r-annotationdbi-spack-v0.15.2": {
        "spec1": "r-annotationdbi-spack-v0.15.1",
        "spec2": "r-annotationdbi-spack-v0.15.2",
        "1_package_name_overlap": 1.0,
        "2_package_name_version_exact": 1.0,
        "3_package_weighted_versions": 1.0,
        "4_parameter_overlap": 0.24444444444444444,
        "5_arch_overlap": 0.9111111111111111
    },
    "r-annotationdbi-spack-v0.15.1-r-annotationdbi-spack-v0.15.3": {
        "spec1": "r-annotationdbi-spack-v0.15.1",
        "spec2": "r-annotationdbi-spack-v0.15.3",
        "1_package_name_overlap": 1.0,
        "2_package_name_version_exact": 1.0,
        "3_package_weighted_versions": 1.0,
        "4_parameter_overlap": 0.24444444444444444,
        "5_arch_overlap": 0.9111111111111111
    },
    "r-annotationdbi-spack-v0.15.1-r-annotationdbi-spack-v0.15.4": {
        "spec1": "r-annotationdbi-spack-v0.15.1",
        "spec2": "r-annotationdbi-spack-v0.15.4",
        "1_package_name_overlap": 1.0,
        "2_package_name_version_exact": 1.0,
        "3_package_weighted_versions": 1.0,
        "4_parameter_overlap": 0.24444444444444444,
        "5_arch_overlap": 0.9111111111111111
    },
    "r-annotationdbi-spack-v0.15.1-r-annotationdbi-spack-v0.16.0": {
        "spec1": "r-annotationdbi-spack-v0.15.1",
        "spec2": "r-annotationdbi-spack-v0.16.0",
        "1_package_name_overlap": 0.967741935483871,
        "2_package_name_version_exact": 0.5775862068965517,
        "3_package_weighted_versions": 0.8279635728932512,
        "4_parameter_overlap": 0.20448028673835125,
        "5_arch_overlap": 0.8817204301075269
    },
    "r-annotationdbi-spack-v0.15.1-r-annotationdbi-spack-v0.16.1": {
        "spec1": "r-annotationdbi-spack-v0.15.1",
        "spec2": "r-annotationdbi-spack-v0.16.1",
        "1_package_name_overlap": 0.967741935483871,
        "2_package_name_version_exact": 0.5775862068965517,
        "3_package_weighted_versions": 0.8279635728932512,
        "4_parameter_overlap": 0.20448028673835125,
        "5_arch_overlap": 0.8817204301075269
    },
    "r-annotationdbi-spack-v0.15.2-r-annotationdbi-spack-v0.15.2": {
        "spec1": "r-annotationdbi-spack-v0.15.2",
        "spec2": "r-annotationdbi-spack-v0.15.2",
        "1_package_name_overlap": 1,
        "2_package_name_version_exact": 1,
        "3_package_weighted_versions": 1,
        "4_parameter_overlap": 1,
        "5_arch_overlap": 1
    },
    "r-annotationdbi-spack-v0.15.2-r-annotationdbi-spack-v0.15.3": {
        "spec1": "r-annotationdbi-spack-v0.15.2",
        "spec2": "r-annotationdbi-spack-v0.15.3",
        "1_package_name_overlap": 1.0,
        "2_package_name_version_exact": 1.0,
        "3_package_weighted_versions": 1.0,
        "4_parameter_overlap": 0.24444444444444444,
        "5_arch_overlap": 0.9111111111111111
    },
    "r-annotationdbi-spack-v0.15.2-r-annotationdbi-spack-v0.15.4": {
        "spec1": "r-annotationdbi-spack-v0.15.2",
        "spec2": "r-annotationdbi-spack-v0.15.4",
        "1_package_name_overlap": 1.0,
        "2_package_name_version_exact": 1.0,
        "3_package_weighted_versions": 1.0,
        "4_parameter_overlap": 0.24444444444444444,
        "5_arch_overlap": 0.9111111111111111
    },
    "r-annotationdbi-spack-v0.15.2-r-annotationdbi-spack-v0.16.0": {
        "spec1": "r-annotationdbi-spack-v0.15.2",
        "spec2": "r-annotationdbi-spack-v0.16.0",
        "1_package_name_overlap": 0.967741935483871,
        "2_package_name_version_exact": 0.5775862068965517,
        "3_package_weighted_versions": 0.8279635728932512,
        "4_parameter_overlap": 0.20448028673835125,
        "5_arch_overlap": 0.8817204301075269
    },
    "r-annotationdbi-spack-v0.15.2-r-annotationdbi-spack-v0.16.1": {
        "spec1": "r-annotationdbi-spack-v0.15.2",
        "spec2": "r-annotationdbi-spack-v0.16.1",
        "1_package_name_overlap": 0.967741935483871,
        "2_package_name_version_exact": 0.5775862068965517,
        "3_package_weighted_versions": 0.8279635728932512,
        "4_parameter_overlap": 0.20448028673835125,
        "5_arch_overlap": 0.8817204301075269
    },
    "r-annotationdbi-spack-v0.15.3-r-annotationdbi-spack-v0.15.3": {
        "spec1": "r-annotationdbi-spack-v0.15.3",
        "spec2": "r-annotationdbi-spack-v0.15.3",
        "1_package_name_overlap": 1,
        "2_package_name_version_exact": 1,
        "3_package_weighted_versions": 1,
        "4_parameter_overlap": 1,
        "5_arch_overlap": 1
    },
    "r-annotationdbi-spack-v0.15.3-r-annotationdbi-spack-v0.15.4": {
        "spec1": "r-annotationdbi-spack-v0.15.3",
        "spec2": "r-annotationdbi-spack-v0.15.4",
        "1_package_name_overlap": 1.0,
        "2_package_name_version_exact": 1.0,
        "3_package_weighted_versions": 1.0,
        "4_parameter_overlap": 0.24444444444444444,
        "5_arch_overlap": 0.9111111111111111
    },
    "r-annotationdbi-spack-v0.15.3-r-annotationdbi-spack-v0.16.0": {
        "spec1": "r-annotationdbi-spack-v0.15.3",
        "spec2": "r-annotationdbi-spack-v0.16.0",
        "1_package_name_overlap": 0.967741935483871,
        "2_package_name_version_exact": 0.5775862068965517,
        "3_package_weighted_versions": 0.8279635728932512,
        "4_parameter_overlap": 0.20448028673835125,
        "5_arch_overlap": 0.8817204301075269
    },
    "r-annotationdbi-spack-v0.15.3-r-annotationdbi-spack-v0.16.1": {
        "spec1": "r-annotationdbi-spack-v0.15.3",
        "spec2": "r-annotationdbi-spack-v0.16.1",
        "1_package_name_overlap": 0.967741935483871,
        "2_package_name_version_exact": 0.5775862068965517,
        "3_package_weighted_versions": 0.8279635728932512,
        "4_parameter_overlap": 0.20448028673835125,
        "5_arch_overlap": 0.8817204301075269
    },
    "r-annotationdbi-spack-v0.15.4-r-annotationdbi-spack-v0.15.4": {
        "spec1": "r-annotationdbi-spack-v0.15.4",
        "spec2": "r-annotationdbi-spack-v0.15.4",
        "1_package_name_overlap": 1,
        "2_package_name_version_exact": 1,
        "3_package_weighted_versions": 1,
        "4_parameter_overlap": 1,
        "5_arch_overlap": 1
    },
    "r-annotationdbi-spack-v0.15.4-r-annotationdbi-spack-v0.16.0": {
        "spec1": "r-annotationdbi-spack-v0.15.4",
        "spec2": "r-annotationdbi-spack-v0.16.0",
        "1_package_name_overlap": 0.967741935483871,
        "2_package_name_version_exact": 0.5775862068965517,
        "3_package_weighted_versions": 0.8279635728932512,
        "4_parameter_overlap": 0.20448028673835125,
        "5_arch_overlap": 0.8817204301075269
    },
    "r-annotationdbi-spack-v0.15.4-r-annotationdbi-spack-v0.16.1": {
        "spec1": "r-annotationdbi-spack-v0.15.4",
        "spec2": "r-annotationdbi-spack-v0.16.1",
        "1_package_name_overlap": 0.967741935483871,
        "2_package_name_version_exact": 0.5775862068965517,
        "3_package_weighted_versions": 0.8279635728932512,
        "4_parameter_overlap": 0.20448028673835125,
        "5_arch_overlap": 0.8817204301075269
    },
    "r-annotationdbi-spack-v0.16.0-r-annotationdbi-spack-v0.16.0": {
        "spec1": "r-annotationdbi-spack-v0.16.0",
        "spec2": "r-annotationdbi-spack-v0.16.0",
        "1_package_name_overlap": 1,
        "2_package_name_version_exact": 1,
        "3_package_weighted_versions": 1,
        "4_parameter_overlap": 1,
        "5_arch_overlap": 1
    },
    "r-annotationdbi-spack-v0.16.0-r-annotationdbi-spack-v0.16.1": {
        "spec1": "r-annotationdbi-spack-v0.16.0",
        "spec2": "r-annotationdbi-spack-v0.16.1",
        "1_package_name_overlap": 1.0,
        "2_package_name_version_exact": 1.0,
        "3_package_weighted_versions": 1.0,
        "4_parameter_overlap": 0.22580645161290322,
        "5_arch_overlap": 0.9139784946236559
    },
    "r-annotationdbi-spack-v0.16.1-r-annotationdbi-spack-v0.16.1": {
        "spec1": "r-annotationdbi-spack-v0.16.1",
        "spec2": "r-annotationdbi-spack-v0.16.1",
        "1_package_name_overlap": 1,
        "2_package_name_version_exact": 1,
        "3_package_weighted_versions": 1,
        "4_parameter_overlap": 1,
        "5_arch_overlap": 1
    }
}