{
    "intersect": [
        [
            "node_os_set",
            "intel ubuntu20.04"
        ],
        [
            "concrete",
            "intel"
        ],
        [
            "node_compiler_set",
            "intel gcc"
        ],
        [
            "node_compiler_version_set",
            "intel gcc Version(9.3.0)"
        ],
        [
            "node",
            "intel"
        ],
        [
            "node_target_set",
            "intel Target(skylake)"
        ],
        [
            "variant_set",
            "intel rpath bool(True)"
        ],
        [
            "node_platform_set",
            "intel linux"
        ],
        [
            "variant_set",
            "intel auto_dispatch none"
        ]
    ],
    "spec1_not_spec2": [
        [
            "version",
            "intel Version(20.0.1)"
        ]
    ],
    "spec2_not_spec1": [
        [
            "version",
            "intel Version(19.1.0)"
        ]
    ],
    "spec1_name": "intel-spack-v0.15.0",
    "spec2_name": "intel-spack-v0.14.1"
}