{
    "intersect": [
        [
            "node_compiler_set",
            "efivar gcc"
        ],
        [
            "node_os_set",
            "efivar ubuntu20.04"
        ],
        [
            "node_target_set",
            "popt Target(skylake)"
        ],
        [
            "node_platform_set",
            "dbxtool linux"
        ],
        [
            "version",
            "efivar Version(37)"
        ],
        [
            "node_os_set",
            "popt ubuntu20.04"
        ],
        [
            "version",
            "dbxtool Version(8)"
        ],
        [
            "node_compiler_set",
            "popt gcc"
        ],
        [
            "concrete",
            "efivar"
        ],
        [
            "version",
            "libiconv Version(1.16)"
        ],
        [
            "node_platform_set",
            "libiconv linux"
        ],
        [
            "node",
            "libiconv"
        ],
        [
            "node",
            "efivar"
        ],
        [
            "node_compiler_version_set",
            "efivar gcc Version(9.3.0)"
        ],
        [
            "node_compiler_version_set",
            "libiconv gcc Version(9.3.0)"
        ],
        [
            "node_platform_set",
            "efivar linux"
        ],
        [
            "node_compiler_version_set",
            "dbxtool gcc Version(9.3.0)"
        ],
        [
            "node_platform_set",
            "popt linux"
        ],
        [
            "node_compiler_set",
            "dbxtool gcc"
        ],
        [
            "node_target_set",
            "libiconv Target(skylake)"
        ],
        [
            "node_compiler_set",
            "libiconv gcc"
        ],
        [
            "concrete",
            "popt"
        ],
        [
            "concrete",
            "dbxtool"
        ],
        [
            "node",
            "popt"
        ],
        [
            "node_target_set",
            "dbxtool Target(skylake)"
        ],
        [
            "node_compiler_version_set",
            "popt gcc Version(9.3.0)"
        ],
        [
            "node",
            "dbxtool"
        ],
        [
            "version",
            "popt Version(1.16)"
        ],
        [
            "node_os_set",
            "dbxtool ubuntu20.04"
        ],
        [
            "node_target_set",
            "efivar Target(skylake)"
        ],
        [
            "concrete",
            "libiconv"
        ],
        [
            "node_os_set",
            "libiconv ubuntu20.04"
        ]
    ],
    "spec1_not_spec2": [],
    "spec2_not_spec1": [],
    "spec1_name": "dbxtool-spack-v0.16.1",
    "spec2_name": "dbxtool-spack-v0.16.0"
}